api/__init__.py
base/__init__.py
core/__init__.py
core/exception.py
core/prefetch_id.py
django_prefetch_id-0.0.1.dist-info/METADATA
django_prefetch_id-0.0.1.dist-info/RECORD
django_prefetch_id-0.0.1.dist-info/WHEEL
django_prefetch_id-0.0.1.dist-info/top_level.txt
djangoprefetchid/__init__.py
